uniparser_buryat/__init__.py
uniparser_buryat/data_nodiacritics/__init__.py
uniparser_buryat/data_strict/__init__.py
uniparser_buryat-1.1.2.dist-info/LICENSE
uniparser_buryat-1.1.2.dist-info/METADATA
uniparser_buryat-1.1.2.dist-info/WHEEL
uniparser_buryat-1.1.2.dist-info/top_level.txt
uniparser_buryat-1.1.2.dist-info/RECORD
